dds_sys.abi3.so
dds/dds.py
dds/__init__.py
pydds-0.0.8.dist-info/top_level.txt
pydds-0.0.8.dist-info/RECORD
pydds-0.0.8.dist-info/METADATA
pydds-0.0.8.dist-info/WHEEL
