Metadata-Version: 2.1
Name: pydds
Version: 0.0.8
Summary: DDS (including BC7) decompression bindings
Classifier: Development Status :: 3 - Alpha
Classifier: License :: OSI Approved :: GNU General Public License v3 or later (GPLv3+)
Classifier: Natural Language :: English
Classifier: Programming Language :: Python :: 3 :: Only
Requires-Dist: Pillow
